sorch/__init__.py
sorch/trainer/__init__.py
sorch/trainer/trainer.py
sorch-0.2.7.dist-info/METADATA
sorch-0.2.7.dist-info/WHEEL
sorch-0.2.7.dist-info/top_level.txt
sorch-0.2.7.dist-info/RECORD
